simond/__init__.py
simond/__main__.py
simond/collector.py
simond/interval.py
simond/si.py
simond/utils.py
simond-0.0.1.dist-info/0
simond-0.0.1.dist-info/METADATA
simond-0.0.1.dist-info/WHEEL
simond-0.0.1.dist-info/entry_points.txt
simond-0.0.1.dist-info/top_level.txt
simond-0.0.1.dist-info/RECORD
