Metadata-Version: 2.1
Name: simond
Version: 0.0.1
Summary: simond - Simple Monitor Daemon, fetches and logs system information
Home-page: https://github.com/ronnyhaase/simon
Author: Ronny Haase
Author-email: ronnyhaase@fastmail.com
License: GPL-3.0-or-later
Project-URL: Bug Tracker, https://github.com/ronnyhaase/simon/issues
Project-URL: Documentation, https://github.com/ronnyhaase/simon/tree/master/daemon
Project-URL: Source Code, https://github.com/ronnyhaase/simon/tree/master/daemon
Platform: UNKNOWN
Classifier: License :: OSI Approved :: GNU General Public License v3 or later (GPLv3+)
Classifier: Topic :: System :: Monitoring
Requires-Python: >=3.6
Requires-Dist: psutil (<6,>=5.7)
Requires-Dist: setuptools
Provides-Extra: dev
Requires-Dist: pylint ; extra == 'dev'
